undetected_geckodriver/__init__.py
undetected_geckodriver/constants.py
undetected_geckodriver/driver.py
undetected_geckodriver/mixins.py
undetected_geckodriver/utils.py
undetected_geckodriver-1.0.7.dist-info/LICENSE
undetected_geckodriver-1.0.7.dist-info/METADATA
undetected_geckodriver-1.0.7.dist-info/WHEEL
undetected_geckodriver-1.0.7.dist-info/top_level.txt
undetected_geckodriver-1.0.7.dist-info/RECORD
