Metadata-Version: 2.1
Name: undetected-geckodriver
Version: 1.0.7
Summary: A Firefox Selenium WebDriver that patches the browser to avoid detection. Bypasses services such as Cloudflare, Distil Networks, and more. Ideal for web scraping, automated testing, and bot development without getting detected.
Home-page: https://github.com/ByteXenon/undetected_geckodriver
Author: ByteXenon
Author-email: ddavi142@asu.edu
License: MIT
Project-URL: Documentation, https://github.com/ByteXenon/undetected_geckodriver#readme
Project-URL: Source, https://github.com/ByteXenon/undetected_geckodriver
Project-URL: Tracker, https://github.com/ByteXenon/undetected_geckodriver/issues
Project-URL: Changelog, https://github.com/ByteXenon/undetected_geckodriver/releases
Keywords: selenium firefox webdriver undetected bypass cloudflare distil web scraping automated testing bot development anti-detection automation browser automation
Classifier: Development Status :: 4 - Beta
Classifier: Intended Audience :: Developers
Classifier: Topic :: Software Development :: Testing
Classifier: Topic :: Software Development :: Libraries :: Python Modules
Classifier: Programming Language :: Python :: 3
Classifier: Programming Language :: Python :: 3.6
Classifier: Programming Language :: Python :: 3.7
Classifier: Programming Language :: Python :: 3.8
Classifier: Programming Language :: Python :: 3.9
Classifier: Programming Language :: Python :: 3.10
Classifier: Programming Language :: Python :: 3.11
Classifier: Programming Language :: Python :: 3.12
Classifier: License :: OSI Approved :: MIT License
Classifier: Operating System :: POSIX :: Linux
Requires-Python: >=3.6
License-File: LICENSE
Requires-Dist: selenium>=4.10.0
Requires-Dist: psutil>=5.8.0
